pytest_elk_reporter.py
pytest_elk_reporter-0.2.4.dist-info/LICENSE
pytest_elk_reporter-0.2.4.dist-info/METADATA
pytest_elk_reporter-0.2.4.dist-info/WHEEL
pytest_elk_reporter-0.2.4.dist-info/entry_points.txt
pytest_elk_reporter-0.2.4.dist-info/top_level.txt
pytest_elk_reporter-0.2.4.dist-info/RECORD
