Metadata-Version: 2.1
Name: pytest-elk-reporter
Version: 0.2.4
Summary: A simple plugin to use with pytest
Home-page: https://github.com/fruch/pytest-elk-reporter
Author: Israel Fruchter
Author-email: israel.fruchter@gmail.com
Maintainer: Israel Fruchter
Maintainer-email: israel.fruchter@gmail.com
License: MIT
Classifier: Development Status :: 4 - Beta
Classifier: Framework :: Pytest
Classifier: Intended Audience :: Developers
Classifier: Topic :: Software Development :: Testing
Classifier: Programming Language :: Python
Classifier: Programming Language :: Python :: 3
Classifier: Programming Language :: Python :: 3.9
Classifier: Programming Language :: Python :: 3.10
Classifier: Programming Language :: Python :: Implementation :: CPython
Classifier: Programming Language :: Python :: Implementation :: PyPy
Classifier: Operating System :: OS Independent
Classifier: License :: OSI Approved :: MIT License
Requires-Python: >=2.7, !=3.0.*, !=3.1.*, !=3.2.*, !=3.3.*
License-File: LICENSE
Requires-Dist: pytest >=3.5.0
Requires-Dist: requests
Requires-Dist: six
